odoo/addons/account_move_cutoff/README.rst
odoo/addons/account_move_cutoff/__init__.py
odoo/addons/account_move_cutoff/__manifest__.py
odoo/addons/account_move_cutoff/i18n/account_move_cutoff.pot
odoo/addons/account_move_cutoff/i18n/es.po
odoo/addons/account_move_cutoff/i18n/fr.po
odoo/addons/account_move_cutoff/models/__init__.py
odoo/addons/account_move_cutoff/models/account_account.py
odoo/addons/account_move_cutoff/models/account_move.py
odoo/addons/account_move_cutoff/models/account_move_line.py
odoo/addons/account_move_cutoff/models/cutoff_period_mixin.py
odoo/addons/account_move_cutoff/models/res_company.py
odoo/addons/account_move_cutoff/models/res_config_settings.py
odoo/addons/account_move_cutoff/readme/CONFIGURE.rst
odoo/addons/account_move_cutoff/readme/DESCRIPTION.rst
odoo/addons/account_move_cutoff/readme/ROADMAP.rst
odoo/addons/account_move_cutoff/readme/USAGE.rst
odoo/addons/account_move_cutoff/static/description/icon.png
odoo/addons/account_move_cutoff/static/description/index.html
odoo/addons/account_move_cutoff/tests/__init__.py
odoo/addons/account_move_cutoff/tests/common.py
odoo/addons/account_move_cutoff/tests/test_account_invoice_cutoff.py
odoo/addons/account_move_cutoff/tests/test_account_move_bank_journal.py
odoo/addons/account_move_cutoff/tests/test_account_move_line.py
odoo/addons/account_move_cutoff/tests/test_account_purchase_invoice_cutoff.py
odoo/addons/account_move_cutoff/tests/test_account_refund_cutoff.py
odoo/addons/account_move_cutoff/tests/test_account_supplier_refund_cutoff.py
odoo/addons/account_move_cutoff/tests/test_cutoff_period_mixin.py
odoo/addons/account_move_cutoff/views/account_account.xml
odoo/addons/account_move_cutoff/views/account_move.xml
odoo/addons/account_move_cutoff/views/account_move_line.xml
odoo/addons/account_move_cutoff/views/res_config_settings.xml
odoo14_addon_account_move_cutoff-14.0.0.1.0.dist-info/METADATA
odoo14_addon_account_move_cutoff-14.0.0.1.0.dist-info/WHEEL
odoo14_addon_account_move_cutoff-14.0.0.1.0.dist-info/top_level.txt
odoo14_addon_account_move_cutoff-14.0.0.1.0.dist-info/RECORD
